javacore_analyser/__init__.py
javacore_analyser/__main__.py
javacore_analyser/abstract_snapshot_collection.py
javacore_analyser/code_snapshot_collection.py
javacore_analyser/constants.py
javacore_analyser/har_file.py
javacore_analyser/java_thread.py
javacore_analyser/javacore.py
javacore_analyser/javacore_analyser_batch.py
javacore_analyser/javacore_analyser_web.py
javacore_analyser/javacore_set.py
javacore_analyser/logging_utils.py
javacore_analyser/properties.py
javacore_analyser/snapshot_collection.py
javacore_analyser/snapshot_collection_collection.py
javacore_analyser/stack_trace.py
javacore_analyser/stack_trace_element.py
javacore_analyser/stack_trace_kind.py
javacore_analyser/thread_snapshot.py
javacore_analyser/tips.py
javacore_analyser/verbose_gc.py
javacore_analyser/data/expand.js
javacore_analyser/data/style.css
javacore_analyser/data/style.js
javacore_analyser/data/html/error.html
javacore_analyser/data/html/processing_data.html
javacore_analyser/data/jquery/chart.js
javacore_analyser/data/jquery/chartjs-adapter-date-fns.bundle.min.js
javacore_analyser/data/jquery/jq.css
javacore_analyser/data/jquery/jquery.mark.min.js
javacore_analyser/data/jquery/jquery.min.js
javacore_analyser/data/jquery/jquery.tablesorter.min.js
javacore_analyser/data/jquery/jquery.tablesorter.widgets.min.js
javacore_analyser/data/jquery/search.js
javacore_analyser/data/jquery/sorting.js
javacore_analyser/data/jquery/theme.blue.css
javacore_analyser/data/jquery/theme.default.min.css
javacore_analyser/data/jquery/wait2scripts.js
javacore_analyser/data/xml/index.xml
javacore_analyser/data/xml/report.xsl
javacore_analyser/data/xml/javacores/javacore.xml
javacore_analyser/data/xml/javacores/javacore.xsl
javacore_analyser/data/xml/threads/thread.xml
javacore_analyser/data/xml/threads/thread.xsl
javacore_analyser/templates/index.html
javacore_analyser-2.5.0.dist-info/METADATA
javacore_analyser-2.5.0.dist-info/WHEEL
javacore_analyser-2.5.0.dist-info/entry_points.txt
javacore_analyser-2.5.0.dist-info/licenses/LICENSE
javacore_analyser-2.5.0.dist-info/RECORD
