Metadata-Version: 2.4
Name: javacore_analyser
Version: 2.5.0
Summary: The tool to review IBM Javacore files
Project-URL: Homepage, https://github.com/IBM/javacore-analyser
Project-URL: Issues, https://github.com/IBM/javacore-analyser/issues
Project-URL: Changelog, https://github.com/IBM/javacore-analyser/blob/main/CHANGELOG.md
Project-URL: Source, https://github.com/IBM/javacore-analyser
Author-email: Krzysztof Kazmierczyk <kazm@ibm.com>, Piotr Aniola <Piotr.Aniola@ibm.com>, Tadeusz Janasiewicz <t.janasiewicz@ibm.com>
License:                                  Apache License
License-File: LICENSE
Classifier: Development Status :: 5 - Production/Stable
Classifier: Environment :: Console
Classifier: Environment :: Web Environment
Classifier: Framework :: Flask
Classifier: Intended Audience :: Customer Service
Classifier: Intended Audience :: System Administrators
Classifier: License :: OSI Approved :: Apache Software License
Classifier: Natural Language :: English
Classifier: Operating System :: OS Independent
Classifier: Programming Language :: Python :: 3
Classifier: Programming Language :: Python :: 3 :: Only
Classifier: Programming Language :: Python :: 3.9
Classifier: Programming Language :: Python :: 3.10
Classifier: Programming Language :: Python :: 3.11
Classifier: Programming Language :: Python :: 3.12
Classifier: Programming Language :: Python :: 3.13
Requires-Python: >=3.9
Requires-Dist: flask
Requires-Dist: haralyzer
Requires-Dist: importlib-resources
Requires-Dist: lxml
Requires-Dist: py7zr
Requires-Dist: pyana
Requires-Dist: tqdm
Requires-Dist: waitress
